roadmapgen2d/__init__.py
roadmapgen2d/__main__.py
roadmapgen2d/__pkginfo__.py
roadmapgen2d/roadmapgen2d_color.py
roadmapgen2d/roadmapgen2d_config.py
roadmapgen2d/roadmapgen2d_map.py
roadmapgen2d/roadmapgen2d_mod_base.py
roadmapgen2d/roadmapgen2d_mod_make_rooms.py
roadmapgen2d/roadmapgen2d_mod_move_diagonal_tails.py
roadmapgen2d/roadmapgen2d_mod_random_points.py
roadmapgen2d/roadmapgen2d_size.py
roadmapgen2d/roadmapgen2d_write_map_to_image.py
roadmapgen2d-0.0.3.dist-info/LICENSE
roadmapgen2d-0.0.3.dist-info/METADATA
roadmapgen2d-0.0.3.dist-info/WHEEL
roadmapgen2d-0.0.3.dist-info/top_level.txt
roadmapgen2d-0.0.3.dist-info/RECORD
