Metadata-Version: 2.1
Name: roadmapgen2d
Version: 0.0.3
Summary: Python App for Generating Roads 2d Maps
Home-page: https://github.com/sea-kg/roadmapgen2d
Author: Evgenii Sopov
Author-email: mrseakg@gmail.com
License: UNKNOWN
Keywords: roadmap,generator,2d
Platform: UNKNOWN
Classifier: Programming Language :: Python :: 3
Classifier: License :: OSI Approved :: Apache Software License
Classifier: Operating System :: OS Independent
Requires-Python: >=3.6
